LICENSE
README.md
setup.cfg
setup.py
nefila/__init__.py
nefila/fortiManagerAnalyzerCore.py
nefila/fortianalyzer.py
nefila/forticare.py
nefila/fortigate.py
nefila/fortimanager.py
nefila/fortiswitch.py
nefila/fortitester.py
nefila/modelmeta.py
nefila/utils.py
nefila.egg-info/PKG-INFO
nefila.egg-info/SOURCES.txt
nefila.egg-info/dependency_links.txt
nefila.egg-info/requires.txt
nefila.egg-info/top_level.txt
tests/__init__.py
tests/test_fortianalyzer.py
tests/test_fortigate.py
tests/test_fortimanager.py
tests/test_fortiswitch.py
tests/test_utils.py